pyrubberband/__init__.py
pyrubberband/pyrb.py
pyrubberband/version.py
pyrubberband-0.4.0.dist-info/LICENSE
pyrubberband-0.4.0.dist-info/METADATA
pyrubberband-0.4.0.dist-info/WHEEL
pyrubberband-0.4.0.dist-info/top_level.txt
pyrubberband-0.4.0.dist-info/RECORD
